{
  "creator": "Yosys 0.9 (git sha1 1979e0b)",
  "modules": {
    "m0x318A": {
      "attributes": {
        "top": 1,
        "src": "/home/user/input/0x318A_V2.v:1"
      },
      "ports": {
        "out": {
          "direction": "output",
          "bits": [ 2 ]
        },
        "in1": {
          "direction": "input",
          "bits": [ 3 ]
        },
        "in2": {
          "direction": "input",
          "bits": [ 4 ]
        },
        "in3": {
          "direction": "input",
          "bits": [ 5 ]
        },
        "in4": {
          "direction": "input",
          "bits": [ 6 ]
        }
      },
      "cells": {
        "$abc$377$auto$blifparse.cc:371:parse_blif$378": {
          "hide_name": 1,
          "type": "$_NOT_",
          "parameters": {
          },
          "attributes": {
          },
          "port_directions": {
            "A": "input",
            "Y": "output"
          },
          "connections": {
            "A": [ 5 ],
            "Y": [ 7 ]
          }
        },
        "$abc$377$auto$blifparse.cc:371:parse_blif$379": {
          "hide_name": 1,
          "type": "$_NOR_",
          "parameters": {
          },
          "attributes": {
          },
          "port_directions": {
            "A": "input",
            "B": "input",
            "Y": "output"
          },
          "connections": {
            "A": [ 7 ],
            "B": [ 4 ],
            "Y": [ 8 ]
          }
        },
        "$abc$377$auto$blifparse.cc:371:parse_blif$380": {
          "hide_name": 1,
          "type": "$_NOR_",
          "parameters": {
          },
          "attributes": {
          },
          "port_directions": {
            "A": "input",
            "B": "input",
            "Y": "output"
          },
          "connections": {
            "A": [ 6 ],
            "B": [ 8 ],
            "Y": [ 9 ]
          }
        },
        "$abc$377$auto$blifparse.cc:371:parse_blif$381": {
          "hide_name": 1,
          "type": "$_NOT_",
          "parameters": {
          },
          "attributes": {
          },
          "port_directions": {
            "A": "input",
            "Y": "output"
          },
          "connections": {
            "A": [ 9 ],
            "Y": [ 10 ]
          }
        },
        "$abc$377$auto$blifparse.cc:371:parse_blif$382": {
          "hide_name": 1,
          "type": "$_NOR_",
          "parameters": {
          },
          "attributes": {
          },
          "port_directions": {
            "A": "input",
            "B": "input",
            "Y": "output"
          },
          "connections": {
            "A": [ 3 ],
            "B": [ 10 ],
            "Y": [ 11 ]
          }
        },
        "$abc$377$auto$blifparse.cc:371:parse_blif$383": {
          "hide_name": 1,
          "type": "$_NOR_",
          "parameters": {
          },
          "attributes": {
          },
          "port_directions": {
            "A": "input",
            "B": "input",
            "Y": "output"
          },
          "connections": {
            "A": [ 7 ],
            "B": [ 3 ],
            "Y": [ 12 ]
          }
        },
        "$abc$377$auto$blifparse.cc:371:parse_blif$384": {
          "hide_name": 1,
          "type": "$_NOR_",
          "parameters": {
          },
          "attributes": {
          },
          "port_directions": {
            "A": "input",
            "B": "input",
            "Y": "output"
          },
          "connections": {
            "A": [ 9 ],
            "B": [ 12 ],
            "Y": [ 13 ]
          }
        },
        "$abc$377$auto$blifparse.cc:371:parse_blif$385": {
          "hide_name": 1,
          "type": "$_NOR_",
          "parameters": {
          },
          "attributes": {
          },
          "port_directions": {
            "A": "input",
            "B": "input",
            "Y": "output"
          },
          "connections": {
            "A": [ 11 ],
            "B": [ 13 ],
            "Y": [ 2 ]
          }
        }
      },
      "netnames": {
        "$abc$377$n10": {
          "hide_name": 1,
          "bits": [ 11 ],
          "attributes": {
          }
        },
        "$abc$377$n11": {
          "hide_name": 1,
          "bits": [ 12 ],
          "attributes": {
          }
        },
        "$abc$377$n12": {
          "hide_name": 1,
          "bits": [ 13 ],
          "attributes": {
          }
        },
        "$abc$377$n6": {
          "hide_name": 1,
          "bits": [ 7 ],
          "attributes": {
          }
        },
        "$abc$377$n7": {
          "hide_name": 1,
          "bits": [ 8 ],
          "attributes": {
          }
        },
        "$abc$377$n8": {
          "hide_name": 1,
          "bits": [ 9 ],
          "attributes": {
          }
        },
        "$abc$377$n9": {
          "hide_name": 1,
          "bits": [ 10 ],
          "attributes": {
          }
        },
        "in1": {
          "hide_name": 0,
          "bits": [ 3 ],
          "attributes": {
            "src": "/home/user/input/0x318A_V2.v:1"
          }
        },
        "in2": {
          "hide_name": 0,
          "bits": [ 4 ],
          "attributes": {
            "src": "/home/user/input/0x318A_V2.v:1"
          }
        },
        "in3": {
          "hide_name": 0,
          "bits": [ 5 ],
          "attributes": {
            "src": "/home/user/input/0x318A_V2.v:1"
          }
        },
        "in4": {
          "hide_name": 0,
          "bits": [ 6 ],
          "attributes": {
            "src": "/home/user/input/0x318A_V2.v:1"
          }
        },
        "out": {
          "hide_name": 0,
          "bits": [ 2 ],
          "attributes": {
            "src": "/home/user/input/0x318A_V2.v:1"
          }
        }
      }
    }
  }
}
